threatexchange/__init__.py
threatexchange/__main__.py
threatexchange/common.py
threatexchange/interface_validation.py
threatexchange/py.typed
threatexchange/cli/.local_install_detection.txt
threatexchange/cli/__init__.py
threatexchange/cli/cli_config.py
threatexchange/cli/cli_state.py
threatexchange/cli/command_base.py
threatexchange/cli/config_cmd.py
threatexchange/cli/dataset_cmd.py
threatexchange/cli/exceptions.py
threatexchange/cli/fetch_cmd.py
threatexchange/cli/hash_cmd.py
threatexchange/cli/helpers.py
threatexchange/cli/label_cmd.py
threatexchange/cli/main.py
threatexchange/cli/match_cmd.py
threatexchange/cli/dataset/__init__.py
threatexchange/cli/dataset/simple_serialization.py
threatexchange/content_type/__init__.py
threatexchange/content_type/content_base.py
threatexchange/content_type/file.py
threatexchange/content_type/photo.py
threatexchange/content_type/text.py
threatexchange/content_type/url.py
threatexchange/content_type/video.py
threatexchange/content_type/preprocess/__init__.py
threatexchange/content_type/preprocess/unletterboxing.py
threatexchange/exchanges/__init__.py
threatexchange/exchanges/auth.py
threatexchange/exchanges/collab_config.py
threatexchange/exchanges/fetch_state.py
threatexchange/exchanges/helpers.py
threatexchange/exchanges/signal_exchange_api.py
threatexchange/exchanges/clients/__init__.py
threatexchange/exchanges/clients/fb_threatexchange/__init__.py
threatexchange/exchanges/clients/fb_threatexchange/api.py
threatexchange/exchanges/clients/fb_threatexchange/api_representations.py
threatexchange/exchanges/clients/fb_threatexchange/descriptor.py
threatexchange/exchanges/clients/fb_threatexchange/threat_updates.py
threatexchange/exchanges/clients/ncmec/__init__.py
threatexchange/exchanges/clients/ncmec/hash_api.py
threatexchange/exchanges/clients/stopncii/__init__.py
threatexchange/exchanges/clients/stopncii/api.py
threatexchange/exchanges/clients/techagainstterrorism/__init__.py
threatexchange-1.2.12.dist-info/METADATA
threatexchange-1.2.12.dist-info/WHEEL
threatexchange-1.2.12.dist-info/entry_points.txt
threatexchange-1.2.12.dist-info/RECORD
