Metadata-Version: 2.4
Name: threatexchange
Version: 1.2.12
Summary: threatexchange is a Python Library and CLI tool for interfacing with Facebook's ThreatExchange.
Project-URL: Homepage, https://www.github.com/facebook/ThreatExchange
Author-email: Facebook <threatexchange@meta.com>
License: BSD
Keywords: facebook,ncmec,pdq,stopncii,threatexchange
Classifier: Development Status :: 5 - Production/Stable
Classifier: Intended Audience :: Developers
Classifier: License :: OSI Approved :: BSD License
Classifier: Programming Language :: Python :: 3.8
Requires-Python: >=3.8
Requires-Dist: dacite
Requires-Dist: faiss-cpu
Requires-Dist: numpy
Requires-Dist: packaging
Requires-Dist: pdqhash
Requires-Dist: pillow
Requires-Dist: python-dateutil
Requires-Dist: requests
Requires-Dist: types-python-dateutil
Requires-Dist: urllib3
Requires-Dist: weighted-levenshtein
Provides-Extra: dev
Requires-Dist: black; extra == 'dev'
Requires-Dist: mypy; extra == 'dev'
Requires-Dist: pytest; extra == 'dev'
Requires-Dist: types-python-dateutil; extra == 'dev'
Requires-Dist: types-requests; extra == 'dev'
Provides-Extra: extensions
Requires-Dist: pdfminer-six; extra == 'extensions'
Requires-Dist: py-tlsh; extra == 'extensions'
Requires-Dist: pytesseract; extra == 'extensions'
Requires-Dist: vpdq; extra == 'extensions'
Provides-Extra: package
Requires-Dist: wheel; extra == 'package'
